pypz/plugins/rmq_io/__init__.py
pypz/plugins/rmq_io/channels.py
pypz/plugins/rmq_io/ports.py
pypz/plugins/rmq_io/utils.py
pypz_rmq_io-0.9.5.dist-info/licenses/LICENSE
pypz_rmq_io-0.9.5.dist-info/METADATA
pypz_rmq_io-0.9.5.dist-info/WHEEL
pypz_rmq_io-0.9.5.dist-info/top_level.txt
pypz_rmq_io-0.9.5.dist-info/RECORD
